CHANGES.txt
MANIFEST.in
README.md
setup.py
wheelcms_simplecontact/__init__.py
wheelcms_simplecontact/contact.py
wheelcms_simplecontact/models.py
wheelcms_simplecontact.egg-info/PKG-INFO
wheelcms_simplecontact.egg-info/SOURCES.txt
wheelcms_simplecontact.egg-info/dependency_links.txt
wheelcms_simplecontact.egg-info/namespace_packages.txt
wheelcms_simplecontact.egg-info/not-zip-safe
wheelcms_simplecontact.egg-info/requires.txt
wheelcms_simplecontact.egg-info/top_level.txt
wheelcms_simplecontact/templates/wheelcms_simplecontact/contact.html