Metadata-Version: 1.1
Name: wheelcms-simplecontact
Version: 1.2
Summary: WheelCMS contact form
Home-page: http://github.com/wheelcms/wheelcms_simplecontact
Author: Ivo van der Wijk
Author-email: wheelcms@in.m3r.nl
License: BSD
Platform: UNKNOWN
Classifier: Programming Language :: Python
